Workbook

Sheet Hist_Financials
A1: Metric (₦ Millions) | B1: FY 2020 | C1: FY 2021 | D1: FY 2022 | E1: FY 2023 | F1: FY 2024 | G1: Primary Source / Note Ref | H1: FY 2020 Ratio | I1: FY 2021 Ratio | J1: FY 2022 Ratio | K1: FY 2023 Ratio | L1: FY 2024 Ratio | N1: 5-Year CAGR (2020-2024)
A2: Revenue | B2: 1029997 | C2: 1383637 | D2: 1618323 | E2: 2208090 | F2: 3580550 | G2: Statement of Profit or Loss, Note 5 | N2: =(F2/B2)^(1/4)-1 -> 0.36545831
A3: Cost of Sales | B3: 437970 | C3: 551019 | D3: 662890 | E3: 1006278 | F3: 1645651 | G3: Statement of Profit or Loss, Note 7
A4: Gross Profit | B4: 592027 | C4: 832618 | D4: 955433 | E4: 1201812 | F4: 1934899 | G4: Statement of Profit or Loss, Subtotal | H4: =B4/B2 -> 0.57478517 | I4: =C4/C2 -> 0.60176043 | J4: =D4/D2 -> 0.59038461 | K4: =E4/E2 -> 0.54427673 | L4: =F4/F2 -> 0.54039156
A5: Operating Profit (EBIT) | B5: 386735 | C5: 585576 | D5: 585876 | E5: 734267 | F5: 1152042 | G5: Statement of Profit or Loss (Profit from operating activities) | H5: =B5/B2 -> 0.37547197 | I5: =C5/C2 -> 0.42321505 | J5: =D5/D2 -> 0.36202662 | K5: =E5/E2 -> 0.33253491 | L5: =F5/F2 -> 0.32175001
A6: Finance Costs | B6: 43989 | C6: 65709 | D6: 130370 | E6: 310962 | F6: 700299 | G6: Statement of Profit or Loss, Note 10.2
A7: Profit for the Year (PAT) | B7: 276068 | C7: 364439 | D7: 382311 | E7: 455583 | F7: 503247 | G7: Statement of Profit or Loss, Bottom line
A8: Cash & Cash Equivalents | B8: 145841 | C8: 240022 | D8: 283275 | E8: 447097 | F8: 449831 | G8: Statement of Financial Position, Note 32.1
A9: Total Debt (Current + Non-Current) | B9: 498127 | C9: 542001 | D9: 706734 | E9: 1012620 | F9: 2631564 | G9: Statement of Financial Position, Note 26 | H9: =(B9-B8)/B16 -> 0.73681194 | I9: =(C9-C8)/C16 -> 0.44110799 | J9: =(D9-D8)/D16 -> 0.59790579 | K9: =(E9-E8)/E16 -> 0.63821578 | L9: =(F9-F8)/F16 -> 1.5809659
A10: Total Equity | B10: 890970 | C10: 983674 | D10: 1080480 | E10: 1725840 | F10: 2175245 | G10: Statement of Financial Position, Total Equity line
A11: Net Cash from Operating Activities | B11: 499021 | C11: 710551 | D11: 682959 | E11: 678789 | F11: 821080 | G11: Statement of Cash Flows, Operating Activities
A12: Acquisition of PPE (Capex) | B12: 119034 | C12: 125487 | D12: 152709 | E12: 140221 | F12: 423045 | G12: Statement of Cash Flows, Investing Activities
A13: Dividends Paid | B13: 272648 | C13: 272648 | D13: 340810 | E13: 337471 | F13: 502580 | G13: Statement of Cash Flows, Financing Activities
A14: Total Cement Volume Sold (Mt) | B14: 25.72 | C14: 29.27 | D14: 27.77 | E14: 27.3 | F14: 27.7 | G14: Annual Report Operational Review / IR Presentation | N14: =(F14/B14)^(1/4)-1 -> 0.018713828
A15: Average Selling Price (₦ / Tonne) | B15: =B2/B14 -> 40046.54 | C15: =C2/C14 -> 47271.507 | D15: =D2/D14 -> 58275.945 | E15: =E2/E14 -> 80882.418 | F15: =F2/F14 -> 129261.73 | G15: Calculated: Group Revenue / Volume Sold | N15: =(F15/B15)^(1/4)-1 -> 0.34037477
A16: EBITDA (Clean Operating) | B16: 478122 | C16: 684592 | D16: 708237 | E16: 886100 | F16: 1380000 | G16: Operating Profit + D&A (IR Highlights) | H16: =B16/B2 -> 0.46419747 | I16: =C16/C2 -> 0.49477717 | J16: =D16/D2 -> 0.43763637 | K16: =E16/E2 -> 0.40129705 | L16: =F16/F2 -> 0.38541565

Sheet Forecast_Model
A1: Driver / Metric | B1: Unit | C1: FY25F | D1: FY26F | E1: FY27F | F1: FY28F | G1: FY29F
A2: Operating Drivers
A3: Cement Volume Growth Rate | B3: % | C3: 0.035 | D3: 0.04 | E3: 0.045 | F3: 0.04 | G3: 0.035
A4: sales Volume (Mt) | B4: Mt | C4: =Hist_Financials!F14 * (1 + C3) -> 28.6695 | D4: =C4 * (1 + D3) -> 29.81628 | E4: =D4 * (1 + E3) -> 31.158013 | F4: =E4 * (1 + F3) -> 32.404333 | G4: =F4 * (1 + G3) -> 33.538485
A5: Realized Price Growth Rate (ASP Inflation) | B5: % | C5: 0.12 | D5: 0.1 | E5: 0.08 | F5: 0.06 | G5: 0.05
A6: Average Realized Price (₦ / Tonne) | B6: ₦ | C6: =Hist_Financials!F15 * (1 + C5) -> 144773.14 | D6: =C6 * (1 + D5) -> 159250.45 | E6: =D6 * (1 + E5) -> 171990.49 | F6: =E6 * (1 + F5) -> 182309.92 | G6: =F6 * (1 + G5) -> 191425.42
A7: Revenue Forecast
A8: Projected Group Revenue | B8: ₦ Millions | C8: =C4 * C6 -> 4150573.6 | D8: =D4 * D6 -> 4748256.2 | E8: =E4 * E6 -> 5358881.9 | F8: =F4 * F6 -> 5907631.4 | G8: =G4 * G6 -> 6420118.4
A9: Operating Expenses & Earnings
A10: Cost of Sales (% of Revenue) | B10: % | C10: 0.465 | D10: 0.46 | E10: 0.455 | F10: 0.45 | G10: 0.45
A11: Cost of Sales | B11: ₦ Millions | C11: =C8 * C10 -> 1930016.7 | D11: =D8 * D10 -> 2184197.8 | E11: =E8 * E10 -> 2438291.3 | F11: =F8 * F10 -> 2658434.1 | G11: =G8 * G10 -> 2889053.3
A12: Gross Profit | B12: ₦ Millions | C12: =C8 - C11 -> 2220556.9 | D12: =D8 - D11 -> 2564058.3 | E12: =E8 - E11 -> 2920590.6 | F12: =F8 - F11 -> 3249197.3 | G12: =G8 - G11 -> 3531065.1
A13: Operating Expenses (SG&A % of Revenue) | B13: % | C13: 0.215 | D13: 0.21 | E13: 0.205 | F13: 0.2 | G13: 0.2
A14: Operating Expenses (SG&A) | B14: ₦ Millions | C14: =C8 * C13 -> 892373.32 | D14: =D8 * D13 -> 997133.79 | E14: =E8 * E13 -> 1098570.8 | F14: =F8 * F13 -> 1181526.3 | G14: =G8 * G13 -> 1284023.7
A15: operating Profit (EBIT) | B15: ₦ Millions | C15: =C12 - C14 -> 1328183.5 | D15: =D12 - D14 -> 1566924.5 | E15: =E12 - E14 -> 1822019.8 | F15: =F12 - F14 -> 2067671 | G15: =G12 - G14 -> 2247041.4
A16: Effective Corporate Tax Rate | B16: % | C16: 0.3 | D16: 0.3 | E16: 0.3 | F16: 0.3 | G16: 0.3
A17: Taxes on Operating Profit (NOPAT adjustment) | B17: ₦ Millions | C17: =C15 * C16 -> 398455.06 | D17: =D15 * D16 -> 470077.36 | E17: =E15 * E16 -> 546605.95 | F17: =F15 * F16 -> 620301.3 | G17: =G15 * G16 -> 674112.43
A18: Net Operating Profit After Tax (NOPAT) | B18: ₦ Millions | C18: =C15 - C17 -> 929728.48 | D18: =D15 - D17 -> 1096847.2 | E18: =E15 - E17 -> 1275413.9 | F18: =F15 - F17 -> 1447369.7 | G18: =G15 - G17 -> 1572929
A19: Free Cash Flow to Firm (FCFF)
A20: Depreciation & Amortisation (% of Revenue) | B20: % | C20: 0.055 | D20: 0.055 | E20: 0.055 | F20: 0.055 | G20: 0.055
A21: Depreciation & Amortisation (D&A) | B21: ₦ Millions | C21: =C8 * C20 -> 228281.55 | D21: =D8 * D20 -> 261154.09 | E21: =E8 * E20 -> 294738.5 | F21: =F8 * F20 -> 324919.73 | G21: =G8 * G20 -> 353106.51
A22: Capital Expenditure (% of Revenue) | B22: % | C22: 0.08 | D22: 0.075 | E22: 0.07 | F22: 0.065 | G22: 0.06
A23: Capital Expenditure (Capex) | B23: ₦ Millions | C23: =C8 * C22 -> 332045.88 | D23: =D8 * D22 -> 356119.21 | E23: =E8 * E22 -> 375121.73 | F23: =F8 * F22 -> 383996.04 | G23: =G8 * G22 -> 385207.11
A24: Change in Net Working Capital (ΔNWC % of Rev) | B24: % | C24: 0.025 | D24: 0.025 | E24: 0.025 | F24: 0.02 | G24: 0.02
A25: Change in Net Working Capital (ΔNWC) | B25: ₦ Millions | C25: =C8 * C24 -> 103764.34 | D25: =D8 * D24 -> 118706.4 | E25: =E8 * E24 -> 133972.05 | F25: =F8 * F24 -> 118152.63 | G25: =G8 * G24 -> 128402.37
A26: Free Cash Flow to Firm (FCFF) | B26: ₦ Millions | C26: =C18 + C21 - C23 - C25 -> 722199.8 | D26: =D18 + D21 - D23 - D25 -> 883175.64 | E26: =E18 + E21 - E23 - E25 -> 1061058.6 | F26: =F18 + F21 - F23 - F25 -> 1270140.8 | G26: =G18 + G21 - G23 - G25 -> 1412426.1
A27: Discounted Period (t in years) | B27: Year | C27: 1 | D27: 2 | E27: 3 | F27: 4 | G27: 5
A28: Weighted Average Cost of Capital (WACC) | B28: % | C28: 0.185 | D28: 0.185 | E28: 0.185 | F28: 0.185 | G28: 0.185
A29: Discount Factor | B29: Multiple | C29: =1 / ((1 + C28) ^ C27) -> 0.84388186 | D29: =1 / ((1 + D28) ^ D27) -> 0.71213659 | E29: =1 / ((1 + E28) ^ E27) -> 0.60095915 | F29: =1 / ((1 + F28) ^ F27) -> 0.50713852 | G29: =1 / ((1 + G28) ^ G27) -> 0.427965
A30: Present Value of Projected FCFF (PV) | B30: ₦ Millions | C30: =C26 * C29 -> 609451.31 | D30: =D26 * D29 -> 628941.69 | E30: =E26 * E29 -> 637652.88 | F30: =F26 * F29 -> 644137.3 | G30: =G26 * G29 -> 604468.91
A32: VALUATION SUMMARY & INTRINSIC VALUE | B32: Unit | C32: Value | D32: Formula / Source Rationale
A33: Cumulative PV of Explicit Forecast (FY25-29) | B33: ₦ Millions | C33: =SUM(C30:G30) -> 3124652.1
A34: Terminal Growth Rate (g) | B34: % | C34: 0.045 | D34: Long-term sustainable GDP growth cap
A35: Undiscounted Terminal Value | B35: ₦ Millions | C35: =(G26 * (1 + C34)) / (C28 - C34) -> 10542752
A36: Present Value of Terminal Value (PV of TV) | B36: ₦ Millions | C36: =C35 * G29 -> 4511928.6
A37: Enterprise Value (EV) | B37: ₦ Millions | C37: =C33 + C36 -> 7636580.7
A38: Less: Total Debt | B38: ₦ Millions | C38: =Hist_Financials!F9 -> 2631564
A39: Plus: Cash & Cash Equivalents | B39: ₦ Millions | C39: =+Hist_Financials!F8 -> 449831
A40: Implied Equity Value | B40: ₦ Millions | C40: =C37 - C38 + C39 -> 5454847.7
A41: Total Ordinary Shares Outstanding | B41: Millions | C41: 16870 | D41: Official Listed Shares (Net of Buybacks)
A42: Estimated Intrinsic Value per Share | B42: ₦ | C42: =(C40 / C41) -> 323.34604
A43: Current Market Reference Price (Valuation Date) | B43: ₦ | C43: 1111 | D43: NGX Quoted Market Price
A44: Implied Upside / (Downside) | B44: % | C44: =(C42 - C43) / C43 -> -0.70895946
A47: INTRINSIC VALUE SENSITIVITY TABLE
A48: Sensitivity: WACC vs. g | B48: WACC \ g | C48: 0.035 | D48: 0.04 | E48: 0.045 | F48: 0.05 | G48: 0.055
A49: Bull Case (Low Risk) | B49: 0.165 | C49: =((NPV($B49, $C$26:$G$26) + (($G$26 * (1 + C$48)) / ($B49 - C$48)) / ((1 + $B49)^5)) - $C$38 + $C$39) / $C$41 -> 376.26993 | D49: =((NPV($B49, $C$26:$G$26) + (($G$26 * (1 + D$48)) / ($B49 - D$48)) / ((1 + $B49)^5)) - $C$38 + $C$39) / $C$41 -> 390.25497 | E49: =((NPV($B49, $C$26:$G$26) + (($G$26 * (1 + E$48)) / ($B49 - E$48)) / ((1 + $B49)^5)) - $C$38 + $C$39) / $C$41 -> 405.40542 | F49: =((NPV($B49, $C$26:$G$26) + (($G$26 * (1 + F$48)) / ($B49 - F$48)) / ((1 + $B49)^5)) - $C$38 + $C$39) / $C$41 -> 421.87331 | G49: =((NPV($B49, $C$26:$G$26) + (($G$26 * (1 + G$48)) / ($B49 - G$48)) / ((1 + $B49)^5)) - $C$38 + $C$39) / $C$41 -> 439.83828
A50: Mid-Bull | B50: 0.175 | C50: =((NPV($B50, $C$26:$G$26) + (($G$26 * (1 + C$48)) / ($B50 - C$48)) / ((1 + $B50)^5)) - $C$38 + $C$39) / $C$41 -> 337.0377 | D50: =((NPV($B50, $C$26:$G$26) + (($G$26 * (1 + D$48)) / ($B50 - D$48)) / ((1 + $B50)^5)) - $C$38 + $C$39) / $C$41 -> 348.65773 | E50: =((NPV($B50, $C$26:$G$26) + (($G$26 * (1 + E$48)) / ($B50 - E$48)) / ((1 + $B50)^5)) - $C$38 + $C$39) / $C$41 -> 361.17161 | F50: =((NPV($B50, $C$26:$G$26) + (($G$26 * (1 + F$48)) / ($B50 - F$48)) / ((1 + $B50)^5)) - $C$38 + $C$39) / $C$41 -> 374.6866 | G50: =((NPV($B50, $C$26:$G$26) + (($G$26 * (1 + G$48)) / ($B50 - G$48)) / ((1 + $B50)^5)) - $C$38 + $C$39) / $C$41 -> 389.32785
A51: Base Case | B51: 0.185 | C51: =((NPV($B51, $C$26:$G$26) + (($G$26 * (1 + C$48)) / ($B51 - C$48)) / ((1 + $B51)^5)) - $C$38 + $C$39) / $C$41 -> 303.12712 | D51: =((NPV($B51, $C$26:$G$26) + (($G$26 * (1 + D$48)) / ($B51 - D$48)) / ((1 + $B51)^5)) - $C$38 + $C$39) / $C$41 -> 312.88798 | E51: =((NPV($B51, $C$26:$G$26) + (($G$26 * (1 + E$48)) / ($B51 - E$48)) / ((1 + $B51)^5)) - $C$38 + $C$39) / $C$41 -> 323.34604 | F51: =((NPV($B51, $C$26:$G$26) + (($G$26 * (1 + F$48)) / ($B51 - F$48)) / ((1 + $B51)^5)) - $C$38 + $C$39) / $C$41 -> 334.57878 | G51: =((NPV($B51, $C$26:$G$26) + (($G$26 * (1 + G$48)) / ($B51 - G$48)) / ((1 + $B51)^5)) - $C$38 + $C$39) / $C$41 -> 346.67556
A52: Mid-Bear | B52: 0.195 | C52: =((NPV($B52, $C$26:$G$26) + (($G$26 * (1 + C$48)) / ($B52 - C$48)) / ((1 + $B52)^5)) - $C$38 + $C$39) / $C$41 -> 273.53689 | D52: =((NPV($B52, $C$26:$G$26) + (($G$26 * (1 + D$48)) / ($B52 - D$48)) / ((1 + $B52)^5)) - $C$38 + $C$39) / $C$41 -> 281.81436 | E52: =((NPV($B52, $C$26:$G$26) + (($G$26 * (1 + E$48)) / ($B52 - E$48)) / ((1 + $B52)^5)) - $C$38 + $C$39) / $C$41 -> 290.64365 | F52: =((NPV($B52, $C$26:$G$26) + (($G$26 * (1 + F$48)) / ($B52 - F$48)) / ((1 + $B52)^5)) - $C$38 + $C$39) / $C$41 -> 300.08186 | G52: =((NPV($B52, $C$26:$G$26) + (($G$26 * (1 + G$48)) / ($B52 - G$48)) / ((1 + $B52)^5)) - $C$38 + $C$39) / $C$41 -> 310.19423
A53: Bear Case (High Risk) | B53: 0.205 | C53: =((NPV($B53, $C$26:$G$26) + (($G$26 * (1 + C$48)) / ($B53 - C$48)) / ((1 + $B53)^5)) - $C$38 + $C$39) / $C$41 -> 247.50145 | D53: =((NPV($B53, $C$26:$G$26) + (($G$26 * (1 + D$48)) / ($B53 - D$48)) / ((1 + $B53)^5)) - $C$38 + $C$39) / $C$41 -> 254.57992 | E53: =((NPV($B53, $C$26:$G$26) + (($G$26 * (1 + E$48)) / ($B53 - E$48)) / ((1 + $B53)^5)) - $C$38 + $C$39) / $C$41 -> 262.1008 | F53: =((NPV($B53, $C$26:$G$26) + (($G$26 * (1 + F$48)) / ($B53 - F$48)) / ((1 + $B53)^5)) - $C$38 + $C$39) / $C$41 -> 270.1069 | G53: =((NPV($B53, $C$26:$G$26) + (($G$26 * (1 + G$48)) / ($B53 - G$48)) / ((1 + $B53)^5)) - $C$38 + $C$39) / $C$41 -> 278.64673
A56: Metric | B56: FY20 | C56: FY21 | D56: FY22 | E56: FY23 | F56: FY24 | G56: FY25F | H56: FY26F | I56: FY27F | J56: FY28F | K56: FY29F
A57: Year | B57: 2020 | C57: 2021 | D57: 2022 | E57: 2023 | F57: 2024 | G57: 2025 | H57: 2026 | I57: 2027 | J57: 2028 | K57: 2029
A58: Revenue (₦ Billion) | B58: =Hist_Financials!B2 / 1000 -> 1029.997 | C58: =Hist_Financials!C2 / 1000 -> 1383.637 | D58: =Hist_Financials!D2 / 1000 -> 1618.323 | E58: =Hist_Financials!E2 / 1000 -> 2208.09 | F58: =Hist_Financials!F2 / 1000 -> 3580.55 | G58: =Forecast_Model!C8 / 1000 -> 4150.5736 | H58: =Forecast_Model!D8 / 1000 -> 4748.2562 | I58: =Forecast_Model!E8 / 1000 -> 5358.8819 | J58: =Forecast_Model!F8 / 1000 -> 5907.6314 | K58: =Forecast_Model!G8 / 1000 -> 6420.1184
A59: EBITDA Margin (%) | B59: =Hist_Financials!B16 / Hist_Financials!B2 -> 0.46419747 | C59: =Hist_Financials!C16 / Hist_Financials!C2 -> 0.49477717 | D59: =Hist_Financials!D16 / Hist_Financials!D2 -> 0.43763637 | E59: =Hist_Financials!E16 / Hist_Financials!E2 -> 0.40129705 | F59: =Hist_Financials!F16 / Hist_Financials!F2 -> 0.38541565 | G59: =(C15+C21)/C8 -> 0.375 | H59: =(D15+D21)/D8 -> 0.385 | I59: =(E15+E21)/E8 -> 0.395 | J59: =(F15+F21)/F8 -> 0.405 | K59: =(G15+G21)/G8 -> 0.405
A61: Metric | B61: FY25F | C61: FY26F | D61: FY27F | E61: FY28F | F61: FY29F
A62: FCFF in ₦ Billions | B62: =C26/1000 -> 722.1998 | C62: =D26/1000 -> 883.17564 | D62: =E26/1000 -> 1061.0586 | E62: =F26/1000 -> 1270.1408 | F62: =G26/1000 -> 1412.4261
A63: Cash Conversion: FCFF / EBITDA % | B63: =C26/(C15 + C21) -> 0.464 | C63: =D26/(D15 + D21) -> 0.48311688 | D63: =E26/(E15 + E21) -> 0.50126582 | E63: =F26/(F15 + F21) -> 0.5308642 | F63: =G26/(G15 + G21) -> 0.54320988

Sheet Comps
A1: Metric | B1: Dangote Cement - DANGCEM | C1: BUA Cement - BUACEMENT | D1: Lafarge Africa - WAPCO | E1: Peer Average
A2: MARKET PRICING & SHARE DATA
A3: Reference Share Price (₦) | B3: 1111 | C3: 112 | D3: 36.5
A4: Ordinary Shares Outstanding (Millions) | B4: 16870 | C4: 33864 | D4: 16108
A5: Market Capitalisation (₦ Millions) | B5: =B3*B4 -> 18742570 | C5: =C3*C4 -> 3792768 | D5: =D3*D4 -> 587942
A6: BALANCE SHEET & ENTERPRISE VALUE
A7: Net Debt (₦ Millions) | B7: 2181733 | C7: 412500 | D7: -65400
A8: Enterprise Value (EV) (₦ Millions) | B8: =B5+B7 -> 20924303 | C8: =C5+C7 -> 4205268 | D8: =D5+D7 -> 522542
A9: FY24 FINANCIAL METRICS
A10: Group Revenue (₦ Millions) | B10: 3580550 | C10: 680200 | D10: 450100
A11: EBITDA (₦ Millions) | B11: 1380000 | C11: 215400 | D11: 145200
A12: Profit After Tax / PAT (₦ Millions) | B12: 503247 | C12: 73200 | D12: 85100
A13: VALUATION MULTIPLES
A14: EV / EBITDA Multiple | B14: =B8/B11 -> 15.162538 | C14: =C8/C11 -> 19.523064 | D14: =D8/D11 -> 3.5987741 | E14: =AVERAGE(C14:D14) -> 11.560919
A15: Price-to-Earnings (P/E) Multiple | B15: =B5/B12 -> 37.243282 | C15: =C5/C12 -> 51.81377 | D15: =D5/D12 -> 6.9088367 | E15: =AVERAGE(C15:D15) -> 29.361304
A16: EV / Revenue Multiple | B16: =B8/B10 -> 5.8438796 | C16: =C8/C10 -> 6.1823993 | D16: =D8/D10 -> 1.1609465 | E16: =AVERAGE(C16:D16) -> 3.6716729
